sphinx_licenseinfo/__init__.py
sphinx_licenseinfo/license-sprite.png
sphinx_licenseinfo/license-sprite@2x.png
sphinx_licenseinfo/license_info.css
sphinx_licenseinfo/license_info.t.html
sphinx_licenseinfo/nodes.py
sphinx_licenseinfo/py.typed
sphinx_licenseinfo/translators.py
sphinx_licenseinfo-0.6.0.post1.dist-info/LICENSE
sphinx_licenseinfo-0.6.0.post1.dist-info/METADATA
sphinx_licenseinfo-0.6.0.post1.dist-info/WHEEL
sphinx_licenseinfo-0.6.0.post1.dist-info/entry_points.txt
sphinx_licenseinfo-0.6.0.post1.dist-info/RECORD
