Metadata-Version: 2.2
Name: sphinx-licenseinfo
Version: 0.6.0.post1
Summary: Sphinx directives for showing license information.
Author-email: Dominic Davis-Foster <dominic@davis-foster.co.uk>
License: MIT
Keywords: documentation,license,sphinx,sphinx-extension
Home-page: https://github.com/sphinx-toolbox/sphinx-licenseinfo
Project-URL: Issue Tracker, https://github.com/sphinx-toolbox/sphinx-licenseinfo/issues
Project-URL: Source Code, https://github.com/sphinx-toolbox/sphinx-licenseinfo
Project-URL: Documentation, https://sphinx-licenseinfo.readthedocs.io/en/latest
Platform: Windows
Platform: macOS
Platform: Linux
Classifier: Development Status :: 4 - Beta
Classifier: Framework :: Sphinx :: Extension
Classifier: Intended Audience :: Developers
Classifier: License :: OSI Approved :: MIT License
Classifier: Operating System :: OS Independent
Classifier: Programming Language :: Python
Classifier: Programming Language :: Python :: 3 :: Only
Classifier: Programming Language :: Python :: 3.7
Classifier: Programming Language :: Python :: 3.8
Classifier: Programming Language :: Python :: 3.9
Classifier: Programming Language :: Python :: 3.10
Classifier: Programming Language :: Python :: 3.11
Classifier: Programming Language :: Python :: 3.12
Classifier: Programming Language :: Python :: Implementation :: CPython
Classifier: Programming Language :: Python :: Implementation :: PyPy
Classifier: Topic :: Documentation
Classifier: Topic :: Documentation :: Sphinx
Classifier: Topic :: Software Development :: Documentation
Classifier: Topic :: Utilities
Classifier: Typing :: Typed
Requires-Python: >=3.7
Requires-Dist: dist-meta>=0.1.2
Requires-Dist: docutils>=0.16
Requires-Dist: domdf-python-tools>=3.0.0
Requires-Dist: jinja2>=2.11.3
Requires-Dist: pychoosealicense>=0.2.0
Requires-Dist: sphinx<7,>=3.2.0
Requires-Dist: sphinx-jinja2-compat>=0.2.0
Requires-Dist: sphinx-toolbox>=2.13.0
